scrapeall/__init__.py
scrapeall/parse.py
scrapeall/utils.py
tests/__init__.py
scrapeall-0.1.2.dist-info/METADATA
scrapeall-0.1.2.dist-info/WHEEL
scrapeall-0.1.2.dist-info/top_level.txt
scrapeall-0.1.2.dist-info/RECORD
