Metadata-Version: 2.1
Name: scrapeall
Version: 0.1.2
Summary: Versatile web scraper for extracting data from both static HTML and JavaScript-rendered sites, using headless browsers for dynamic content.
Home-page: https://github.com/arunism/scrapeall
Author: Arun Ghimire
Author-email: thearunism@gmail.com
License: MIT
Classifier: License :: OSI Approved :: MIT License
Classifier: Programming Language :: Python :: 3.10
Classifier: Operating System :: OS Independent
Requires-Python: >=3.10
Requires-Dist: pyppeteer ==2.0.0
Requires-Dist: beautifulsoup4 ==4.12.3
Requires-Dist: requests ==2.32.3
Requires-Dist: omegaconf ==2.3.0
